{
  "muckrock": {
    "index": 0,
    "name": "MuckRock",
    "keyword": "MR",
    "multitab": false,
    "url": "https://www.muckrock.com/search/?q=",
    "show": true
  },
  "fbi": {
    "index": 1,
    "name": "FBI",
    "keyword": "FBI",
    "multitab": false,
    "url": "https://vault.fbi.gov/search?SearchableText=",
    "show": true
  },
  "cia": {
    "index": 2,
    "name": "CIA",
    "keyword": "CIA",
    "multitab": false,
    "url": "https://www.cia.gov/library/readingroom/advanced-search-view?keyword=",
    "show": true
  },
  "mary-ferrell": {
    "index": 3,
    "name": "Mary Ferrell",
    "keyword": "MF",
    "multitab": false,
    "url": "https://maryferrell.org/search.html?q=",
    "show": true
  },
  "nsia": {
    "index": 4,
    "name": "NSIA",
    "keyword": "NSIA",
    "multitab": false,
    "url": "https://archive.org/details/nationalsecurityarchive?and%5B%5D=",
    "show": true
  },
  "document-cloud": {
    "index": 5,
    "name": "Document Cloud",
    "keyword": "DC",
    "multitab": false,
    "url": "https://www.documentcloud.org/public/search/",
    "show": true
  }
}